Arase/Globals.py
Arase/__init__.py
Arase/Electrons/ReadOmni.py
Arase/Electrons/StackPlot.py
Arase/Electrons/__init__.py
Arase/HEP/CalculatePADs.py
Arase/HEP/DataAvailability.py
Arase/HEP/DeleteDate.py
Arase/HEP/DownloadData.py
Arase/HEP/GetPitchAngle.py
Arase/HEP/PADAvailability.py
Arase/HEP/Read3D.py
Arase/HEP/ReadCDF.py
Arase/HEP/ReadIndex.py
Arase/HEP/ReadOmni.py
Arase/HEP/ReadPAD.py
Arase/HEP/RebuildDataIndex.py
Arase/HEP/SaveMirrorAlts.py
Arase/HEP/SavePADs.py
Arase/HEP/__init__.py
Arase/Ions/ReadOmni.py
Arase/Ions/StackPlot.py
Arase/Ions/__init__.py
Arase/LEPe/CalculatePADs.py
Arase/LEPe/DataAvailability.py
Arase/LEPe/DeleteDate.py
Arase/LEPe/DownloadData.py
Arase/LEPe/GetPitchAngle.py
Arase/LEPe/PADAvailability.py
Arase/LEPe/Read3D.py
Arase/LEPe/ReadCDF.py
Arase/LEPe/ReadIndex.py
Arase/LEPe/ReadOmni.py
Arase/LEPe/ReadPAD.py
Arase/LEPe/RebuildDataIndex.py
Arase/LEPe/SaveMirrorAlts.py
Arase/LEPe/SavePADs.py
Arase/LEPe/__init__.py
Arase/LEPi/CalculatePADs.py
Arase/LEPi/DataAvailability.py
Arase/LEPi/DeleteDate.py
Arase/LEPi/DownloadData.py
Arase/LEPi/GetPitchAngle.py
Arase/LEPi/PADAvailability.py
Arase/LEPi/Read3D.py
Arase/LEPi/ReadCDF.py
Arase/LEPi/ReadIndex.py
Arase/LEPi/ReadOmni.py
Arase/LEPi/ReadPAD.py
Arase/LEPi/RebuildDataIndex.py
Arase/LEPi/SaveMirrorAlts.py
Arase/LEPi/SavePADs.py
Arase/LEPi/__init__.py
Arase/MEPe/CalculatePADs.py
Arase/MEPe/DataAvailability.py
Arase/MEPe/DeleteDate.py
Arase/MEPe/DownloadData.py
Arase/MEPe/GetPitchAngle.py
Arase/MEPe/PADAvailability.py
Arase/MEPe/Read3D.py
Arase/MEPe/ReadCDF.py
Arase/MEPe/ReadIndex.py
Arase/MEPe/ReadOmni.py
Arase/MEPe/ReadPAD.py
Arase/MEPe/RebuildDataIndex.py
Arase/MEPe/SaveMirrorAlts.py
Arase/MEPe/SavePADs.py
Arase/MEPe/__init__.py
Arase/MEPi/CalculatePADs.py
Arase/MEPi/DataAvailability.py
Arase/MEPi/DeleteDate.py
Arase/MEPi/DownloadData.py
Arase/MEPi/GetPitchAngle.py
Arase/MEPi/PADAvailability.py
Arase/MEPi/Read3D.py
Arase/MEPi/ReadCDF.py
Arase/MEPi/ReadIndex.py
Arase/MEPi/ReadOmni.py
Arase-0.1.13.dist-info/LICENSE
Arase-0.1.13.dist-info/METADATA
Arase-0.1.13.dist-info/WHEEL
Arase-0.1.13.dist-info/top_level.txt
Arase-0.1.13.dist-info/RECORD
