Metadata-Version: 2.1
Name: Arase
Version: 0.1.13
Summary: A module for downloading and reading Arase spacecraft data.
Home-page: https://github.com/mattkjames7/Arase
Author: Matthew Knight James
Author-email: mattkjames7@gmail.com
License: UNKNOWN
Platform: UNKNOWN
Classifier: Programming Language :: Python :: 3
Classifier: License :: OSI Approved :: MIT License
Classifier: Operating System :: POSIX
License-File: LICENSE
Requires-Dist: DateTimeTools >=0.2.0
Requires-Dist: PyFileIO
Requires-Dist: PyGeopack
Requires-Dist: RecarrayTools
Requires-Dist: cdflib
Requires-Dist: matplotlib
Requires-Dist: numpy
Requires-Dist: scipy
